mcp_server_http_request/__init__.py
mcp_server_http_request/__main__.py
mcp_server_http_request/server.py
mcp_server_http_request-0.1.0.dist-info/METADATA
mcp_server_http_request-0.1.0.dist-info/WHEEL
mcp_server_http_request-0.1.0.dist-info/entry_points.txt
mcp_server_http_request-0.1.0.dist-info/licenses/LICENSE
mcp_server_http_request-0.1.0.dist-info/RECORD
