Metadata-Version: 2.4
Name: mcp-server-http-request
Version: 0.1.0
Summary: A Model Context Protocol server providing tools to make HTTP requests (GET, POST, PUT, PATCH, DELETE)
Author-email: Esteban Safranchik <esteban@statespace.com>, Gavin Chan <gavin@statespace.com>
License: MIT
License-File: LICENSE
Keywords: api,automation,http,llm,mcp,rest
Classifier: Development Status :: 4 - Beta
Classifier: Intended Audience :: Developers
Classifier: License :: OSI Approved :: MIT License
Classifier: Programming Language :: Python :: 3
Classifier: Programming Language :: Python :: 3.10
Requires-Python: >=3.10
Requires-Dist: httpx<0.28
Requires-Dist: mcp>=1.1.3
Requires-Dist: pydantic>=2.0.0
